{
  "id": "princess-luminaces-guide-to-the-pony-pantheon",
  "title": "Princess Luminace's Guide to the Pony Pantheon",
  "version": "0.9.1",
  "compatibility": {
    "minimum": "11",
    "verified": "11"
  },
  "relationships": {
    "requires": [
      {
        "id": "ponyfinder-foundryvtt-module",
        "type": "module",
        "compatibility": {}
      }
    ],
    "systems": [
      {
        "id": "pf2e",
        "type": "system",
        "compatibility": {}
      }
    ],
    "recommends": [
      {
        "id": "pf2e-perception",
        "type": "module",
        "compatibility": {}
      },
      {
        "id": "battlezoo-ancestries-dragons-pf2e",
        "type": "module",
        "compatibility": {}
      },
      {
        "id": "pf2e-extension-pack",
        "type": "module",
        "compatibility": {}
      }
    ],
    "conflicts": [
      {
        "id": "pf2e-expansion-pack",
        "type": "module",
        "compatibility": {}
      }
    ]
  },
  "description": "Princess Luminace's Guide to the Pony Pantheon 2nd Edition converted to FoundryVTT. Contains: 2 player ancestries, 13 Ancestry Feats, 1 trap, 2 Archetypes (1 partial and 1 full), 5 tables, 3 Journals, 4 new and 8 updated deities, 22 Class Feats, 6 new Heritages, 13 Mutations, 9 Spells, and a partridge in a pear tree.",
  "authors": [
    {
      "name": "David Silver",
      "discord": "davidsilver",
      "flags": {}
    },
    {
      "name": "Teraunce Foaloke",
      "discord": "teraunce",
      "flags": {}
    }
  ],
  "url": "example.com",
  "packs": [
    {
      "name": "plog-journals",
      "label": "PLOG-Journals",
      "path": "packs/journals",
      "type": "JournalEntry",
      "ownership": {
        "PLAYER": "OBSERVER",
        "ASSISTANT": "OWNER"
      },
      "system": "pf2e",
      "flags": {}
    },
    {
      "name": "plog-tables",
      "label": "PLOG-Tables",
      "path": "packs/tables",
      "type": "RollTable",
      "ownership": {
        "PLAYER": "OBSERVER",
        "ASSISTANT": "OWNER"
      },
      "system": "pf2e",
      "flags": {}
    },
    {
      "name": "plog-actors",
      "label": "PLOG-Actors",
      "path": "packs/actors",
      "type": "Actor",
      "ownership": {
        "PLAYER": "OBSERVER",
        "ASSISTANT": "OWNER"
      },
      "system": "pf2e",
      "flags": {}
    },
    {
      "name": "plog-spells",
      "label": "PLOG-Spells",
      "path": "packs/spells",
      "type": "Item",
      "ownership": {
        "PLAYER": "OBSERVER",
        "ASSISTANT": "OWNER"
      },
      "system": "pf2e",
      "flags": {}
    },
    {
      "name": "plog-everything-else",
      "label": "PLOG-Everything Else",
      "path": "packs/everything-else",
      "type": "Item",
      "ownership": {
        "PLAYER": "OBSERVER",
        "ASSISTANT": "OWNER"
      },
      "system": "pf2e",
      "flags": {}
    }
  ],
  "flags": {
    "princess-luminaces-guide-to-the-pony-pantheon": {
      "pf2e-homebrew": {
        "creatureTraits": {
          "lumidragon": "Luminous Dragon",
          "ponysatyr": "Pony Satyr"
        },
        "featTraits": {
          "lumidragon": "Luminous Dragon",
          "ponysatyr": "Pony Satyr",
          "class": "Class"
        }
      }
    }
  },
  "packFolders": [
    {
      "name": "Ponyfinder",
      "sorting": "m",
      "folders": [
        {
          "name": "Princess Luminace's Guide to the Pony Pantheon",
          "sorting": "m",
          "packs": [
            "plog-actors",
            "plog-tables",
            "plog-everything-else",
            "plog-journals",
            "plog-spells"
          ]
        }
      ],
      "packs": []
    }
  ],
  "manifest": "https://github.com/Teraunce/pony-pantheon/releases/latest/download/module.json",
  "download": "https://github.com/Teraunce/pony-pantheon/releases/latest/download/princess-luminaces-guide-to-the-pony-pantheon.zip"
}